icecoal/__init__.py
icecoal/const.py
icecoal/expression.py
icecoal/icecoal.py
icecoal/utilfuns.py
icecoal-1.0.5.dist-info/LICENSE
icecoal-1.0.5.dist-info/METADATA
icecoal-1.0.5.dist-info/WHEEL
icecoal-1.0.5.dist-info/top_level.txt
icecoal-1.0.5.dist-info/RECORD
