Metadata-Version: 2.1
Name: icecoal
Version: 1.0.5
Summary: Lightweight SQL database
Home-page: https://github.com/ppml38/icecoal
Author: Prakash Maria Liju P
Author-email: ppml38@gmail.com
License: UNKNOWN
Platform: UNKNOWN
Classifier: Programming Language :: Python :: 3
Classifier: License :: OSI Approved :: MIT License
Classifier: Operating System :: OS Independent
Requires-Python: >=3.6
